[{"items":[{"url":"codemirror/index_407.html","text":"CodeMirror for 4.0.7","icon":"codemirror.png","desc":"CodeMirror wrapper working with Extjs 4.0.7."},{"url":"codemirror/index_411.html","text":"CodeMirror for 4.1.1","icon":"codemirror.png","desc":"CodeMirror wrapper working with Extjs 4.1.x."},{"url":"htmleditor/index.html","text":"HtmlEditor plugins","icon":"htmleditor_plugins.png","desc":"Html editor plugins."},{"url":"uploadfile/index.html","text":"Delete file upload","icon":"imagefilefield.png","desc":"Delete uploaded file."},{"url":"imageupload/index.html","text":"Image file upload","icon":"imagefilefield.png","desc":"Image file upload with preview button."},{"url":"pivotgrid/pivot.html","text":"Pivot grid","icon":"pivotgrid.png","desc":"Powerful pivot grid with multiple aggregation posibilities."},{"url":"pivotgrid/summary.html","text":"Pivot grid with summary","icon":"pivotgrid.png","desc":"Powerful pivot grid with multiple aggregation posibilities."},{"url":"pivotgrid/reconfigurable.html","text":"Pivot grid configurator","icon":"pivotgrid_configurator.png","desc":"Pivot grid configurator to check all features.","status":"new"}],"title":"Components Examples"}]